discord/ext/paginators/__init__.py
discord/ext/paginators/_types.py
discord/ext/paginators/base_paginator.py
discord/ext/paginators/button_paginator.py
discord/ext/paginators/modal_paginator.py
discord/ext/paginators/select_paginator.py
discord/ext/paginators/utils.py
discord_py_paginators-0.2.1.dist-info/LICENSE
discord_py_paginators-0.2.1.dist-info/METADATA
discord_py_paginators-0.2.1.dist-info/WHEEL
discord_py_paginators-0.2.1.dist-info/top_level.txt
discord_py_paginators-0.2.1.dist-info/RECORD
