Metadata-Version: 2.1
Name: discord-py-paginators
Version: 0.2.1
Summary: Extension for discord.py that provides various paginators.
Author: Soheab_
License: Mozilla Public License
Project-URL: Documentation, https://discord-py-paginators.readthedocs.io/
Project-URL: Github, https://github.com/Soheab/discord-py-paginators
Project-URL: Discord, https://discord.gg/yCzcfju
Classifier: Development Status :: 5 - Production/Stable
Classifier: Natural Language :: English
Classifier: Typing :: Typed
Classifier: License :: OSI Approved :: Mozilla Public License 2.0 (MPL 2.0)
Classifier: Programming Language :: Python :: 3 :: Only
Classifier: Programming Language :: Python :: 3.9
Classifier: Programming Language :: Python :: 3.10
Classifier: Programming Language :: Python :: 3.11
Requires-Python: >=3.9
License-File: LICENSE
Requires-Dist: discord.py<3.0.0,>=2.2.0
Provides-Extra: docs
Requires-Dist: sphinx<8.0.0,>=7.0.0; extra == "docs"
Requires-Dist: furo<2024.0.0,>=2023.9.10; extra == "docs"
Requires-Dist: sphinx-autodoc-typehints<2.0.0,>=1.25.0; extra == "docs"
Requires-Dist: sphinx-toolbox<4.0,>=3.5; extra == "docs"
Provides-Extra: dev
Requires-Dist: black; extra == "dev"
Requires-Dist: ruff; extra == "dev"
Requires-Dist: typing_extensions; extra == "dev"
Requires-Dist: pyright; extra == "dev"
Provides-Extra: modalpaginator
Requires-Dist: discord-ext-modal-paginator; extra == "modalpaginator"
